ilcctl/__init__.py
ilcctl/bulb.py
ilcctl/errors.py
ilcctl/ilcctl.py
ilcctl-1.0.1.dist-info/METADATA
ilcctl-1.0.1.dist-info/WHEEL
ilcctl-1.0.1.dist-info/entry_points.txt
ilcctl-1.0.1.dist-info/top_level.txt
ilcctl-1.0.1.dist-info/RECORD
